bfscan/__init__.py
bfscan/filter.py
bfscan/logo.py
bfscan/model.py
bfscan/parallel.py
bfscan/cli/__init__.py
bfscan/cli/build_filters.py
bfscan/cli/build_model.py
bfscan/cli/search.py
bfscan/utils/__init__.py
bfscan-0.0.4.dist-info/LICENSE
bfscan-0.0.4.dist-info/METADATA
bfscan-0.0.4.dist-info/WHEEL
bfscan-0.0.4.dist-info/entry_points.txt
bfscan-0.0.4.dist-info/top_level.txt
bfscan-0.0.4.dist-info/RECORD
