Metadata-Version: 2.1
Name: bfscan
Version: 0.0.4
Summary: bfscan is designed to detect foodborne pathogens using bloom filter and machine learning
Author: Thiago Pereira de Oliveira Carvalho, Frederico Schmitt Kremer
Author-email: thg.baum@gmail.com, fred.s.kremer@gmail.com
Keywords: bioinformatics bloom filter data science foodborne pathogen
License-File: LICENSE
Requires-Dist: pandas
Requires-Dist: Biopython
Requires-Dist: tqdm
Requires-Dist: numpy
Requires-Dist: bloom-filter2
Requires-Dist: scikit-learn
Requires-Dist: imbalanced-learn
Requires-Dist: twine
Requires-Dist: matplotlib
Requires-Dist: xgboost
